pgnotifier/__init__.py
pgnotifier/notify.py
pgnotifier-0.0.10.dist-info/LICENSE
pgnotifier-0.0.10.dist-info/METADATA
pgnotifier-0.0.10.dist-info/WHEEL
pgnotifier-0.0.10.dist-info/top_level.txt
pgnotifier-0.0.10.dist-info/RECORD
