Metadata-Version: 2.1
Name: pgnotifier
Version: 0.0.10
Summary: A simple little module to capture, process, and dispatch Postgresql NOTIFY streams
Author-email: Ben Howell <ben@psychstudio.com>
Project-URL: Homepage, https://github.com/benhowell/pgnotifier
Project-URL: README, https://github.com/benhowell/pgnotifier/blob/main/README.md
Project-URL: TODO, https://github.com/benhowell/pgnotifier/blob/main/TODO.md
Project-URL: Issues, https://github.com/benhowell/pgnotifier/issues
Classifier: Programming Language :: Python :: 3
Classifier: License :: OSI Approved :: MIT License
Classifier: Operating System :: OS Independent
Requires-Python: >=3.10
License-File: LICENSE
Requires-Dist: pyrsistent >=0.20.0
Requires-Dist: psycopg >=3.2.1
